Metadata-Version: 2.1
Name: freegeoip-client
Version: 1.0.5
Summary: FreeGeoIp's RESTful API client for Python
Home-page: https://github.com/kfurjan/python-freegeoip-client
Author: Kevin Furjan
Author-email: kfurjan@gmail.com
License: MIT
Project-URL: GitHub Project, https://github.com/kfurjan/python-freegeoip-client
Project-URL: Issue Tracker, https://github.com/kfurjan/python-freegeoip-client/issues
Keywords: FreeGeoIp,Client,REST API Client
Platform: UNKNOWN
Classifier: Intended Audience :: Developers
Classifier: Programming Language :: Python
Classifier: Programming Language :: Python :: 3
Classifier: Operating System :: OS Independent
Classifier: License :: OSI Approved :: MIT License
Classifier: Topic :: Software Development :: Libraries :: Python Modules
Requires-Python: >=3.6
